abbrcompress/__init__.py
abbrcompress/core.py
examples/demo.py
examples/openai_prompt_usage.py
abbrcompress-0.1.4.dist-info/METADATA
abbrcompress-0.1.4.dist-info/WHEEL
abbrcompress-0.1.4.dist-info/top_level.txt
abbrcompress-0.1.4.dist-info/RECORD
