Metadata-Version: 2.4
Name: abbrcompress
Version: 0.1.4
Summary: Token-saving abbreviation compressor for OpenAI LLM prompts
Author: Louis Mai
Requires-Python: >=3.8
Requires-Dist: tiktoken
